topsearch/__init__.py
topsearch/analysis/__init__.py
topsearch/analysis/batch_selection.py
topsearch/analysis/graph_properties.py
topsearch/analysis/minima_properties.py
topsearch/analysis/pair_selection.py
topsearch/analysis/roughness.py
topsearch/data/__init__.py
topsearch/data/coordinates.py
topsearch/data/kinetic_transition_network.py
topsearch/data/model_data.py
topsearch/global_optimisation/__init__.py
topsearch/global_optimisation/basin_hopping.py
topsearch/global_optimisation/perturbations.py
topsearch/minimisation/__init__.py
topsearch/minimisation/lbfgs.py
topsearch/plotting/__init__.py
topsearch/plotting/disconnectivity.py
topsearch/plotting/network.py
topsearch/plotting/stationary_points.py
topsearch/potentials/__init__.py
topsearch/potentials/atomic.py
topsearch/potentials/bayesian_optimisation.py
topsearch/potentials/dataset_fitting.py
topsearch/potentials/dft.py
topsearch/potentials/force_fields.py
topsearch/potentials/gaussian_process.py
topsearch/potentials/ml_potentials.py
topsearch/potentials/potential.py
topsearch/potentials/test_functions.py
topsearch/sampling/__init__.py
topsearch/sampling/exploration.py
topsearch/similarity/__init__.py
topsearch/similarity/molecular_similarity.py
topsearch/similarity/similarity.py
topsearch/transition_states/__init__.py
topsearch/transition_states/hybrid_eigenvector_following.py
topsearch/transition_states/nudged_elastic_band.py
topsearch-0.0.3.dist-info/LICENSE
topsearch-0.0.3.dist-info/METADATA
topsearch-0.0.3.dist-info/WHEEL
topsearch-0.0.3.dist-info/RECORD
