Metadata-Version: 2.1
Name: topsearch
Version: 0.0.3
Summary: A Python package for topographical analysis of machine learning models and physical systems
Home-page: https://github.com/IBM/topography-searcher/
License: MIT
Keywords: machine-learning,chemistry,topography,landscapes,explainable-ai
Author: Luke Dicks
Author-email: luke.dicks@ibm.com
Requires-Python: >=3.10,<3.13
Classifier: License :: OSI Approved :: MIT License
Classifier: Programming Language :: Python :: 3
Classifier: Programming Language :: Python :: 3.10
Classifier: Programming Language :: Python :: 3.11
Classifier: Programming Language :: Python :: 3.12
Requires-Dist: ase (>=3.22.1,<4.0.0)
Requires-Dist: matplotlib (>=3.8.3,<4.0.0)
Requires-Dist: networkx (>=3.2.1,<4.0.0)
Requires-Dist: nptyping (>=2.5.0,<3.0.0)
Requires-Dist: numpy (>=1.26.1,<2.0.0)
Requires-Dist: rdkit (>=2023.9.4,<2024.0.0)
Requires-Dist: scikit-learn (>=1.3.2,<2.0.0)
Requires-Dist: scipy (>=1.11.3,<2.0.0)
Project-URL: Repository, https://github.com/IBM/topography-searcher/
